django_holonet-0.0.2.dist-info/DESCRIPTION.rst
django_holonet-0.0.2.dist-info/METADATA
django_holonet-0.0.2.dist-info/metadata.json
django_holonet-0.0.2.dist-info/RECORD
django_holonet-0.0.2.dist-info/top_level.txt
django_holonet-0.0.2.dist-info/WHEEL
holonet_django/__init__.py
holonet_django/apps.py
holonet_django/exceptions.py
holonet_django/fields.py
holonet_django/handlers.py
holonet_django/models.py
holonet_django/settings.py
holonet_django/signals.py
holonet_django/validators.py
holonet_django/management/__init__.py
holonet_django/management/commands/__init__.py
tests/__init__.py
tests/models.py
tests/test_handlers.py
tests/test_models.py
tests/test_settings.py
tests/test_signals.py
tests/test_validators.py
