Metadata-Version: 2.0
Name: django-holonet
Version: 0.0.2
Summary: This package is used to control holonet from a django project.
Home-page: https://github.com/webkom/django-holonet
Author: Abakus Webkom
Author-email: webkom@abakus.no
License: MIT
Keywords: django-holonet
Platform: UNKNOWN
Classifier: Environment :: Web Environment
Classifier: Framework :: Django
Classifier: Intended Audience :: Developers
Classifier: License :: OSI Approved :: MIT License
Classifier: Natural Language :: English
Classifier: Programming Language :: Python :: 2
Classifier: Programming Language :: Python :: 2.7
Classifier: Programming Language :: Python :: 3
Classifier: Programming Language :: Python :: 3.4
